circlepy/__init__.py
circlepy/async_client.py
circlepy/client.py
circlepy/headless_client.py
circlepy/client_models/__init__.py
circlepy/client_models/comment_likes.py
circlepy/client_models/comments.py
circlepy/client_models/likes.py
circlepy/client_models/members.py
circlepy/client_models/posts.py
circlepy/client_models/spaces.py
circlepy/headless_models/__init__.py
circlepy/headless_models/auth.py
circlepy/headless_models/base_api_client.py
circlepy/headless_models/bookmarks_api.py
circlepy/headless_models/chat_api.py
circlepy/headless_models/comments_api.py
circlepy/headless_models/community_links_api.py
circlepy/headless_models/community_members_api.py
circlepy/headless_models/cookies_api.py
circlepy/headless_models/courses_api.py
circlepy/headless_models/events_api.py
circlepy/headless_models/flagged_contents_api.py
circlepy/headless_models/home_api.py
circlepy/headless_models/invitation_links_api.py
circlepy/headless_models/live_streams_api.py
circlepy/headless_models/notifications_api.py
circlepy/headless_models/page_profile_fields_api.py
circlepy/headless_models/posts_api.py
circlepy/headless_models/quizzes_api.py
circlepy/headless_models/search_api.py
circlepy/headless_models/space_members_api.py
circlepy/headless_models/spaces_api.py
circlepy/headless_models/helper/__init__.py
circlepy/headless_models/helper/tiptap.py
circlepy-0.5.0.dist-info/METADATA
circlepy-0.5.0.dist-info/WHEEL
circlepy-0.5.0.dist-info/top_level.txt
circlepy-0.5.0.dist-info/RECORD
