Metadata-Version: 2.4
Name: circlepy
Version: 0.5.0
Summary: Circle.so API made easy with async support for efficient Python integration.
Home-page: https://github.com/atomimus/CirclePy
Author: Waleed Salah Aldin
Author-email: waleed9salah@gmail.com
License: MIT
Classifier: Programming Language :: Python :: 3
Classifier: License :: OSI Approved :: MIT License
Classifier: Operating System :: OS Independent
Requires-Python: >=3.7
Requires-Dist: requests
Requires-Dist: aiohttp
Requires-Dist: pillow
Requires-Dist: commonmark
Dynamic: author
Dynamic: author-email
Dynamic: classifier
Dynamic: description
Dynamic: description-content-type
Dynamic: home-page
Dynamic: requires-dist
Dynamic: requires-python
Dynamic: summary
